emojichat/__init__.py
emojichat/typing.py
emojichat/emoji/__init__.py
emojichat/emoji/demoji.py
emojichat/emoji/emoji.py
emojichat/gpt/__init__.py
emojichat/gpt/chat.py
emojichat/prompts/__init__.py
emojichat/prompts/demoji_prompt.py
emojichat/prompts/emoji_prompt.py
emojichat-0.0.1.dist-info/LICENSE
emojichat-0.0.1.dist-info/METADATA
emojichat-0.0.1.dist-info/WHEEL
emojichat-0.0.1.dist-info/top_level.txt
emojichat-0.0.1.dist-info/RECORD
