Metadata-Version: 2.1
Name: emojichat
Version: 0.0.1
Summary: Chat with emojis
Author: Zecheng Zhang
Author-email: zechengzhang97@gmail.com
Keywords: emoji,gpt,chatgpt
Requires-Python: >=3.7
License-File: LICENSE
Requires-Dist: pytest
Requires-Dist: pre-commit
Requires-Dist: openai
Requires-Dist: tqdm
